suzerain/__init__.py
suzerain/classifier.py
suzerain/cli.py
suzerain/insights.py
suzerain/models.py
suzerain/parser.py
suzerain-0.4.0.dist-info/licenses/LICENSE
suzerain-0.4.0.dist-info/METADATA
suzerain-0.4.0.dist-info/WHEEL
suzerain-0.4.0.dist-info/entry_points.txt
suzerain-0.4.0.dist-info/top_level.txt
suzerain-0.4.0.dist-info/RECORD
