Metadata-Version: 2.4
Name: suzerain
Version: 0.4.0
Summary: What kind of AI ruler are you? Analyze your Claude Code governance patterns.
Author: Amadeus Woo
License: MIT
Project-URL: Homepage, https://github.com/amadeuswoo/suzerain
Project-URL: Documentation, https://github.com/amadeuswoo/suzerain#readme
Project-URL: Repository, https://github.com/amadeuswoo/suzerain
Project-URL: Issues, https://github.com/amadeuswoo/suzerain/issues
Keywords: ai,governance,claude,analytics,behavior,cli
Classifier: Development Status :: 3 - Alpha
Classifier: Intended Audience :: Developers
Classifier: Topic :: Software Development :: Libraries :: Python Modules
Classifier: Programming Language :: Python :: 3.10
Classifier: Programming Language :: Python :: 3.11
Classifier: Programming Language :: Python :: 3.12
Classifier: License :: OSI Approved :: MIT License
Requires-Python: >=3.10
License-File: LICENSE
Provides-Extra: dev
Requires-Dist: pytest>=8.0; extra == "dev"
Requires-Dist: pytest-cov>=4.0; extra == "dev"
Requires-Dist: black>=24.0; extra == "dev"
Requires-Dist: ruff>=0.1; extra == "dev"
Dynamic: license-file
